tchan.py
tchan-0.1.4.dist-info/LICENSE
tchan-0.1.4.dist-info/METADATA
tchan-0.1.4.dist-info/WHEEL
tchan-0.1.4.dist-info/entry_points.txt
tchan-0.1.4.dist-info/top_level.txt
tchan-0.1.4.dist-info/RECORD
