Metadata-Version: 2.1
Name: tchan
Version: 0.1.4
Summary: Scrape Telegram public channels (Python library + CLI)
Home-page: https://github.com/PythonicCafe/tchan/
Author: Álvaro Justen
Author-email: alvarojusten@gmail.com
License: GNU Lesser General Public License v3 (LGPLv3)
Keywords: telegram scraping social-media
Classifier: Intended Audience :: Developers
Classifier: License :: OSI Approved :: GNU Lesser General Public License v3 (LGPLv3)
Classifier: Operating System :: OS Independent
Classifier: Programming Language :: Python
Classifier: Programming Language :: Python :: 3
Classifier: Programming Language :: Python :: 3 :: Only
Classifier: Programming Language :: Python :: 3.7
Classifier: Programming Language :: Python :: 3.8
Classifier: Programming Language :: Python :: 3.9
Classifier: Programming Language :: Python :: 3.10
Classifier: Programming Language :: Python :: 3.11
Classifier: Topic :: Internet :: WWW/HTTP
Classifier: Topic :: Internet :: WWW/HTTP :: Dynamic Content
Requires-Python: >=3.7
License-File: LICENSE
Requires-Dist: lxml
Requires-Dist: requests
Provides-Extra: cli
Requires-Dist: loguru ; extra == 'cli'
Requires-Dist: tqdm ; extra == 'cli'
Provides-Extra: dev
Requires-Dist: autoflake ; extra == 'dev'
Requires-Dist: black ; extra == 'dev'
Requires-Dist: flake8 ; extra == 'dev'
Requires-Dist: ipython ; extra == 'dev'
Requires-Dist: isort ; extra == 'dev'
Requires-Dist: pytest ; extra == 'dev'
Requires-Dist: twine ; extra == 'dev'
Requires-Dist: wheel ; extra == 'dev'
